cafeMachine.v
module cafeMachine(
	input clk, input rst, input [1:0]in, // 00 = none, 01 = nickel , 10 = dime, 11 = quarter
	output reg out, output reg[4:0]change
);

parameter s0 = 0;
parameter s5 = 1;
parameter s10 = 2;
parameter s15 = 3;
parameter s20 = 4;
parameter s25 = 5;
parameter s30 = 6;
parameter s35 = 7;
parameter s40 = 8;
parameter s45 = 9;
parameter s50 = 10;
parameter s55 = 11;
parameter s60 = 12;
parameter s65 = 13;
parameter s70 = 14;

reg[3:0] c_state, n_state;

always@ (posedge clk)
	begin
		if(rst == 1)
			c_state <= 0;
		else
			c_state = n_state;
	end

always@(*)
	case(c_state)
		s0: //state 0 
		if(in == 2'b01)
			begin
				n_state = s5;
				out = 0;
				//change = 5'b00000;
			end
		else if(in == 2'b10)
			begin
				n_state = s10;
				out = 0;
				//change = 5'b00000;
			end
		else if(in == 2'b11)
			begin
				n_state = s25;
				out = 0;
				//change = 5'b00000;
			end
		else
			n_state = s0;

		s5: //state 0 
		if(in == 2'b01)
			begin
				n_state = s10;
			end
		else if(in == 2'b10)
			begin
				n_state = s15;
			end
		else if(in == 2'b11)
			begin
				n_state = s30;
			end
		else
			n_state = s5;

		s10: //state 0 
		if(in == 2'b01)
			begin
				n_state = s15;
			end
		else if(in == 2'b10)
			begin
				n_state = s20;
			end
		else if(in == 2'b11)
			begin
				n_state = s35;
			end
		else
			n_state = s10;

		s15: //state 0 
		if(in == 2'b01)
			begin
				n_state = s20;
			end
		else if(in == 2'b10)
			begin
				n_state = s25;
			end
		else if(in == 2'b11)
			begin
				n_state = s40;
			end
		else
			n_state = s15;

		s20: //state 0 
		if(in == 2'b01)
			begin
				n_state = s25;
			end
		else if(in == 2'b10)
			begin
				n_state = s35;
			end
		else if(in == 2'b11)
			begin
				n_state = s45;
			end
		else
			n_state = s20;

		s25: //state 0 
		if(in == 2'b01)
			begin
				n_state = s30;
			end
		else if(in == 2'b10)
			begin
				n_state = s35;
			end
		else if(in == 2'b11)
			begin
				n_state = s50;
			end
		else
			n_state = s25;

		s30: //state 0 
		if(in == 2'b01)
			begin
				n_state = s35;
			end
		else if(in == 2'b10)
			begin
				n_state = s45;
			end
		else if(in == 2'b11)
			begin
				n_state = s55;
			end
		else
			n_state = s30;

		s35: //state 0 
		if(in == 2'b01)
			begin
				n_state = s40;
			end
		else if(in == 2'b10)
			begin
				n_state = s45;
			end
		else if(in == 2'b11)
			begin
				n_state = s60;
			end
		else
			n_state = s35;

		s40: //state 0 
		if(in == 2'b01)
			begin
				n_state = s45;
			end
		else if(in == 2'b10)
			begin
				n_state = s50;
			end
		else if(in == 2'b11)
			begin
				n_state = s65;
			end
		else
			n_state = s40;


		s45: //state 0 
		if(in == 2'b01)
			begin
				n_state = s50;
			end
		else if(in == 2'b10)
			begin
				n_state = s55;
			end
		else if(in == 2'b11)
			begin
				n_state = s70;
			end
		else
			n_state = s45;

		s50:
		begin 
			n_state = s0;
			out = 1;
			change = 5'b00000;
		end

		s55:
		begin 
			n_state = s0;
			out = 1;
			change = 5'b00101;
		end

		s60:
		begin 
			n_state = s0;
			out = 1;
			change = 5'b01010;
		end

		s65:
		begin 
			n_state = s0;
			out = 1;
			change = 5'b01111;
		end

		s70:
		begin 
			n_state = s0;
			out = 1;
			change = 5'b10100;
		end
	endcase
endmodule

cafeMachine_tb.v
`timescale 1ns/100ps
module cafeMachine_tb;
//inputs
reg clk;
reg[1:0] in;
reg rst;
//output
wire out;
wire[4:0] change;
cafeMachine uut(
.clk(clk),
.rst(rst),
.in(in),
.out(out),
.change(change)
);
initial begin
//initialise inputs
$dumpfile("cafeMachine.vcd");
$dumpvars(0,cafeMachine_tb);
clk=0;
rst=0;
#5 rst = 1;
#5 rst = 0;
end
always #5 clk = ~clk; 
initial
begin
in = 2'b00;
#20 in = 2'b10;
#10 in = 2'b10;
#10 in = 2'b01;
#10 in = 2'b11;
#100 $finish;
end
endmodule

simulation/modelsim/cafeMachine.vcd
$date
	Thu Dec 15 15:25:09 2022
$end
$version
	ModelSim Version 10.5b
$end
$timescale
	100ps
$end

$scope module cafeMachine_tb $end
$var reg 1 ! clk $end
$var reg 2 " in [1:0] $end
$var reg 1 # rst $end
$var wire 1 $ out $end
$var wire 1 % change [4] $end
$var wire 1 & change [3] $end
$var wire 1 ' change [2] $end
$var wire 1 ( change [1] $end
$var wire 1 ) change [0] $end

$scope module uut $end
$var parameter 32 * s0 $end
$var parameter 32 + s5 $end
$var parameter 32 , s10 $end
$var parameter 32 - s15 $end
$var parameter 32 . s20 $end
$var parameter 32 / s25 $end
$var parameter 32 0 s30 $end
$var parameter 32 1 s35 $end
$var parameter 32 2 s40 $end
$var parameter 32 3 s45 $end
$var parameter 32 4 s50 $end
$var parameter 32 5 s55 $end
$var parameter 32 6 s60 $end
$var parameter 32 7 s65 $end
$var parameter 32 8 s70 $end
$var wire 1 9 clk $end
$var wire 1 : rst $end
$var wire 1 ; in [1] $end
$var wire 1 < in [0] $end
$var reg 1 = out $end
$var reg 5 > change [4:0] $end
$var reg 4 ? c_state [3:0] $end
$var reg 4 @ n_state [3:0] $end
$upscope $end
$upscope $end
$enddefinitions $end
#0
$dumpvars
0!
b0 "
0#
x=
bx >
bx ?
bx @
b0 *
b1 +
b10 ,
b11 -
b100 .
b101 /
b110 0
b111 1
b1000 2
b1001 3
b1010 4
b1011 5
b1100 6
b1101 7
b1110 8
x$
x)
x(
x'
x&
x%
0<
0;
0:
09
$end
#50
1#
1!
1:
19
b0 ?
b0 @
#100
0#
0!
0:
09
#150
1!
19
#200
b10 "
0!
1;
09
b10 @
0=
0$
#250
1!
19
b10 ?
b100 @
#300
0!
09
#350
1!
19
b100 ?
b111 @
#400
b1 "
0!
1<
0;
09
b101 @
#450
1!
19
b101 ?
b110 @
#500
b11 "
0!
1;
09
b1010 @
#550
1!
19
b1010 ?
b0 @
1=
b0 >
1$
0)
0(
0'
0&
0%
#600
0!
09
#650
1!
19
b0 ?
b101 @
0=
0$
#700
0!
09
#750
1!
19
b101 ?
b1010 @
#800
0!
09
#850
1!
19
b1010 ?
b0 @
1=
1$
#900
0!
09
#950
1!
19
b0 ?
b101 @
0=
0$
#1000
0!
09
#1050
1!
19
b101 ?
b1010 @
#1100
0!
09
#1150
1!
19
b1010 ?
b0 @
1=
1$
#1200
0!
09
#1250
1!
19
b0 ?
b101 @
0=
0$
#1300
0!
09
#1350
1!
19
b101 ?
b1010 @
#1400
0!
09
#1450
1!
19
b1010 ?
b0 @
1=
1$
